{
  "default": {
    "workflow": "default",
    "metrics": {
      "type": "recommendation",
      "metrics": {
        "top_1_hit_rate": 1.0,
        "top_3_hit_rate": 1.0,
        "top_5_hit_rate": 1.0,
        "average_hit_rate": 1.0,
        "total_scenarios": 2,
        "top_1_hits": 2,
        "top_3_hits": 2,
        "top_5_hits": 2
      },
      "data_info": {
        "evaluated_count": 2,
        "original_simulation_count": 2,
        "original_ground_truth_count": 384
      }
    },
    "execution_time": 31.063770055770874,
    "avg_time_per_task": 15.531885027885437,
    "num_tasks": 2,
    "dataset": "yelp",
    "success": true
  },
  "self_refine": {
    "workflow": "self_refine",
    "metrics": {
      "type": "recommendation",
      "metrics": {
        "top_1_hit_rate": 0.5,
        "top_3_hit_rate": 1.0,
        "top_5_hit_rate": 1.0,
        "average_hit_rate": 0.8333333333333334,
        "total_scenarios": 2,
        "top_1_hits": 1,
        "top_3_hits": 2,
        "top_5_hits": 2
      },
      "data_info": {
        "evaluated_count": 2,
        "original_simulation_count": 2,
        "original_ground_truth_count": 384
      }
    },
    "execution_time": 14.3197181224823,
    "avg_time_per_task": 7.15985906124115,
    "num_tasks": 2,
    "dataset": "yelp",
    "success": true
  },
  "openagi": {
    "workflow": "openagi",
    "metrics": {
      "type": "recommendation",
      "metrics": {
        "top_1_hit_rate": 1.0,
        "top_3_hit_rate": 1.0,
        "top_5_hit_rate": 1.0,
        "average_hit_rate": 1.0,
        "total_scenarios": 2,
        "top_1_hits": 2,
        "top_3_hits": 2,
        "top_5_hits": 2
      },
      "data_info": {
        "evaluated_count": 2,
        "original_simulation_count": 2,
        "original_ground_truth_count": 384
      }
    },
    "execution_time": 12.404843091964722,
    "avg_time_per_task": 6.202421545982361,
    "num_tasks": 2,
    "dataset": "yelp",
    "success": true
  }
}